README.rst
setup.cfg
setup.py
flask_journey/__init__.py
flask_journey/blueprint_bundle.py
flask_journey/exceptions.py
flask_journey/journey.py
flask_journey/utils.py
flask_journey.egg-info/PKG-INFO
flask_journey.egg-info/SOURCES.txt
flask_journey.egg-info/dependency_links.txt
flask_journey.egg-info/not-zip-safe
flask_journey.egg-info/requires.txt
flask_journey.egg-info/top_level.txt