Metadata-Version: 1.1
Name: flask-journey
Version: 0.1.3
Summary: Flask blueprint management
Home-page: https://github.com/rbw0/flask-journey
Author: Robert Wikman
Author-email: rbw@vault13.org
License: MIT
Download-URL: https://github.com/rbw0/flask-journey/tarball/0.1.3
Platform: any
Classifier: Environment :: Web Environment
Classifier: Intended Audience :: Developers
Classifier: License :: OSI Approved :: BSD License
Classifier: Operating System :: OS Independent
Classifier: Programming Language :: Python
Classifier: Topic :: Internet :: WWW/HTTP :: Dynamic Content
Classifier: Topic :: Software Development :: Libraries :: Python Modules
